commanding/__init__.py
commanding/cli_manager.py
commanding/command.py
commanding/command_manager.py
commanding/exceptions.py
commanding/log_window_handler.py
commanding/type.py
commanding-0.0.2.dist-info/METADATA
commanding-0.0.2.dist-info/WHEEL
commanding-0.0.2.dist-info/top_level.txt
commanding-0.0.2.dist-info/RECORD
