Metadata-Version: 2.1
Name: commanding
Version: 0.0.2
Summary: 명령줄과 로그를 편리하게 구현할수 있는 라이브러리
Classifier: Programming Language :: Python :: 3
Requires-Python: >=3.10
